DESCRIPTION
LICENSE.txt
MANIFEST.in
README
VERSION
requirements.txt
setup.cfg
setup.py
./toflerdb/__init__.py
./toflerdb/config.py
./toflerdb.egg-info/PKG-INFO
./toflerdb.egg-info/SOURCES.txt
./toflerdb.egg-info/dependency_links.txt
./toflerdb.egg-info/entry_points.txt
./toflerdb.egg-info/requires.txt
./toflerdb.egg-info/top_level.txt
./toflerdb/apiserver/__init__.py
./toflerdb/apiserver/apiserver.py
./toflerdb/apiserver/handlers/__init__.py
./toflerdb/apiserver/handlers/basehandler.py
./toflerdb/apiserver/handlers/generalsearchhandler.py
./toflerdb/apiserver/handlers/queryhandler.py
./toflerdb/apiserver/handlers/uploadfactshandler.py
./toflerdb/apiserver/handlers/uploadontologyhandler.py
./toflerdb/core/__init__.py
./toflerdb/core/api.py
./toflerdb/core/entry_maker.py
./toflerdb/core/eraser.py
./toflerdb/core/graphquery.py
./toflerdb/core/onto_maker.py
./toflerdb/dbutils/__init__.py
./toflerdb/dbutils/dbutils.py
./toflerdb/dbutils/eraser.py
./toflerdb/dbutils/eternity.py
./toflerdb/dbutils/snapshot.py
./toflerdb/dbutils/tasks.py
./toflerdb/scripts/__init__.py
./toflerdb/scripts/bootstrap.py
./toflerdb/scripts/sample.py
./toflerdb/scripts/sampleconfig.py
./toflerdb/utils/__init__.py
./toflerdb/utils/api.py
./toflerdb/utils/cache.py
./toflerdb/utils/collection.py
./toflerdb/utils/common.py
./toflerdb/utils/config.py
./toflerdb/utils/db.py
./toflerdb/utils/elastic.py
./toflerdb/utils/exceptions.py
./toflerdb/utils/idmanagement.py
./toflerdb/utils/locks.py
./toflerdb/utils/logger.py
./toflerdb/utils/rdfreader.py
./toflerdb/utils/templatizedid.py
toflerdb/resources/data/gctest_facts.rdf
toflerdb/resources/data/gctest_ontology.rdf
toflerdb/resources/data/to.common.ontology.rdf
toflerdb/resources/data/ussec.ontology.rdf
toflerdb/resources/data/ussec.sample-facts.rdf
toflerdb/resources/dbpatches/toflerdb_bulk_task_queue.sql
toflerdb/resources/dbpatches/toflerdb_eternity.sql
toflerdb/resources/dbpatches/toflerdb_ontology.sql
toflerdb/resources/dbpatches/toflerdb_snapshot.es
toflerdb/resources/dbpatches/toflerdb_snapshot.node.es
toflerdb/resources/dbpatches/toflerdb_worker.sql