Metadata-Version: 1.1
Name: toflerdb
Version: 0.0.3
Summary: ToflerDB
Home-page: http://www.toflerdb.com
Author: Team Tofler
Author-email: devteam@tofler.in
License: GNU AGPLv3
Platform: UNKNOWN
Classifier: Development Status :: 4 - Beta
Classifier: Intended Audience :: Developers
Classifier: Programming Language :: Python :: 2.7
Classifier: Operating System :: OS Independent
